{
	"PREFIX": "§8[§6Latuno§8] §r",
	"localeCode": "en_US",
	"name": "English",
	
	"values": {
	
	"raw.blue": "§1Blue",
	"raw.blue.color": "§1",
	"raw.green": "§2Green",
	"raw.green.color": "§2",
	"raw.cyan": "§3Cyan",
	"raw.cyan.color": "§3",
	"raw.red": "§4Red",
	"raw.red.color": "§4",
	"raw.purple": "§5Purple",
	"raw.purple.color": "§5",
	"raw.orange": "§6Orange",
	"raw.orange.color": "§6",
	"raw.gray": "§8Green",
	"raw.gray.color": "§8",
	"raw.black": "§0Black",
	"raw.black.color": "§0",
	"raw.lime": "§aLime",
	"raw.lime.color": "§a",
	"raw.aqua": "§bAqua",
	"raw.aqua.color": "§b",
	"raw.pink": "§dPink",
	"raw.pink.color": "§d",
	"raw.yellow": "§eYellow",
	"raw.yellow.color": "§e",
	"raw.white": "§fWhite",
	"raw.white.color": "§f",
	"raw.gold": "§gGold",
	"raw.gold.color": "§g",
	
	"raw.map": "Map",
	"raw.gold": "Gold",
	"raw.drops": "Drops",
	"raw.ranked": "Ranked",
	
	"bedwars.category.fast": "Rush",
	"bedwars.category.pickaxes": "Pickaxes",
	"bedwars.category.blocks": "Blocks",
	"bedwars.category.armor": "Armor",
	"bedwars.category.weapons": "Weapons",
	"bedwars.category.bows": "Bows",
	"bedwars.category.food": "Food",
	"bedwars.category.misc": "Misc",
	
	"item.lore.price": "§r§aPrice: #0##1#x #2#",
	
	"ui.title.settings": "§cSettings",
	"ui.title.clans": "§cClans",
	"ui.title.stats": "§eStats",
	"ui.title.spectate": "§eSpectate",
	"ui.title.cosmetics": "§5Cosmetics",
	"ui.title.teleporter": "§eTeleporter",
	"ui.title.hidePlayer": "§ePlayer§r§7-§eHider",
	
	"ui.title.purchase.newShop": "§cBuy a Shop",
	"ui.title.purchase.newStick": "§cBuy a Stick",
	
	"ui.text.purchase": "§cBuy stuff here for a good BedWars round§8.",
	"ui.text.stats.bedwars": "§eRounds: §9#0#\n§eKills: §9#1#\n§eDeaths: §9#2#\n§eK/D: §9#3#\n§eWins: §9#4#\n§eDefeats: §9#5#\n§eDestroyed beds: §9#6#\n\n§eWin-Chance: §9#7#",
	
	"ui.text.voteForDrops": "§7Item Drops",
	"ui.text.voteForGold": "§6Gold Voting",
	
	"ui.text.playerHider": "{PREFIX} §cHide §7or §ashow §7all §ePlayers§7!",
	"ui.error.clans.alreadyExists": "§cThis §eClan§c already exists§7.",
	"ui.text.noPlayersFound": "§cNo players found§7.",
	
	"ui.button.close": "§cClose",
	"ui.button.accept": "§aAccept",
	"ui.button.deny": "§cDeny",
	"ui.button.confirm": "§aConfirm",
	"ui.button.abort": "§cAbort",
	"ui.button.back": "§cBack",
	"ui.button.enable": "§aOn",
	"ui.button.disable": "§cOff",
	
	"ui.button.settings": "§cSettings",
	"ui.button.maps": "§dMaps",
	"ui.button.chooseShopMethod": "§7Select an Shop",
	"ui.button.showCoordinates": "§7Show coordinates",
	
	"ui.button.clans.search": "§7Search an §cClan",
	"ui.button.clans.create": "§7Create an §cClan",
	"ui.button.clans.invite": "§7Invite a §eSpieler",
	"ui.button.clans.requests": "§7Invites §8( §e#0#§8 )",
	"ui.button.clans.info": "§7Clan Info",
	"ui.button.clans.manage": "§7Manage your §eClan",
	"ui.button.clans.leave": "§7Leave your §eClan",
	
	"ui.button.clans.manage.image": "§aSelect an §eImage§7.",
	"ui.button.clans.manage.tag_color": "§aSelect an §eTag§7-§eColor",
	"ui.button.clans.manage.clam_color": "§aSelect an §eClam§7-§eColor",
	"ui.button.clans.manage.members": "§dMembers",
	"ui.button.clans.manage.delete": "§4Delete your Clan",
	
	"message.lobby.hideAll": "{PREFIX} §cAll §ePlayers§c are now §einvisible§7.",
	"message.lobby.showAll": "{PREFIX} §aAll §ePlayers§a are now §evisible§7.",
	
	"message.broadcast.1": "{PREFIX} §7Follow us on §bTwitter§7: §e@LatunoNET§r",
	"message.broadcast.2": "{PREFIX} §7Join our Discord under §ehttps://Latuno.net/discord/§7.",
	"message.broadcast.3": "{PREFIX} §7It is recommended to play with the §eClassic§7-§eUI §7.",
	
	"message.alreadyInTeam": "{PREFIX} §cYou are already in this §dTeam§8.",
	"message.teamIsFull": "{PREFIX} §cThis §dTeam§c is already full§8.",
	"message.notInGame": "{PREFIX} §4You are not §cInGame§8.",
	
	"message.alreadyVoted": "{PREFIX} §cYou have already voted§8.",
	"message.voteForItemDrops": "{PREFIX} §aYou have voted for §7Item Drops§8.",
	"message.devoteForItemDrops": "{PREFIX} §cYou have voted against §7Item Drops§8.",
	
	"message.voteForGold": "{PREFIX} §aYou have voted for §6Gold§8.",
	"message.devoteForGold": "{PREFIX} §cYou have voted against §6Gold§8.",
	
	"message.ownCoins": "{PREFIX} §eYour §aCoins§7:§e #0#",
	"message.addedCoins": "{PREFIX} §aYou have the player §6#0# §e#1# Coins §agiven§7!",
	"message.removedCoins": "{PREFIX} §cYou have the player §6#0# §e#1# Coins §cremoved§7!",
	
	"message.supremeToVoter": "{PREFIX} §eYou got §97 days §bSupreme §ebecause you have 30 or more votes.\n§gHave fun with it§7.",
	"message.playerNotExists": "{PREFIX} §cThis player don't exists§7.",
    "message.notEnoughCoins": "{PREFIX} §cNot enough coins§7.",
	
	"message.cantSelectYourself": "{PREFIX} §cYou can't select yourself§7!",
	"message.clanWasCreated": "{PREFIX} §aThe Clan§e #0# §awas created with the Tag §e#1#§7.",
	"message.clanNotFound": "{PREFIX} §cThis §eClan§c was not found§7.",
	"message.clanInviteSent": "{PREFIX} §aYou sent an §eClan§8-§eInvite§a to §e#0#§7.",
	"message.clanInvite": "{PREFIX} §aYou have recived an §eClan§8-§eInvite§a from §e#0#§7!",
	"message.clanLeft": "{PREFIX} §cYou have left the §eClan§7.",
	
	"message.joinQueue": "{PREFIX} §aYou have joined the §eQueue§7.",
	"message.leftQueue": "{PREFIX} §cYou have left the §eQueue§7.",
	
	"message.cloudNoServer": "{PREFIX} §cNo Server found§8.",
	"message.cloudOffline": "{PREFIX} §cThis §eServer§c is currently §4offline§8.",
	"message.cloudRunning": "{PREFIX} §cThis §eRound §chas already started§8.",
	"message.cloudMaintenance": "{PREFIX} §cThis §eServer§c is currently under §4Maintenance§8.",
	"message.cloudStaff": "{PREFIX} §cThis §eServer§c is only for §1Teammember§8.",
	"message.cloudBeta": "{PREFIX} §cThis §eServer§c is only for §aBeta Tester§8.",
	"message.cloudYoutuber": "{PREFIX} §cThis §eServer§c is only for §5YouTuber§8.",
	"message.cloudPremium": "{PREFIX} §cThis §eServer§c is only for §6Premium Player§8.",
	
	"message.playerDied": "{PREFIX} §cThe Player§r #0# §cdied§8.",
	"message.youKilled": "{PREFIX} §aYou have killed§r #0#§8.",
	"message.youKilledBy": "{PREFIX} §cYou was killed by§r #0#§8.",
	"message.playerKilledBy": "{PREFIX} §cThe Player§r #0# §cwas killed by§r #1#§8.",
	"message.youAreDead": "{PREFIX} §cYou are eliminated because your bed no longer exists§8.",
	"message.youDied": "{PREFIX} §cYou died§8.",
	
	"message.settingsWasSaved": "{PREFIX} §aYour §eSettings§a was saved§8.",
	"message.settingsSavedError": "{PREFIX} §cYour §eSettings§c could not be saved§8.",
	
	"message.shopWasSuccessfulChanged": "{PREFIX} §aYour Shop was changed§8.",
	"message.shopWasNotChanged": "{PREFIX} §cYour Shop was not changed§8.",
	
	"message.stickWasSuccessfulChanged": "{PREFIX} §aYour Stick was changed§8.",
	"message.stickWasNotChanged": "{PREFIX} §cYour Stick was not changed§8.",
	
	"no.perms": "§cYou don't have the permissions to do this§7!",
	
	"lobby.hide.button.show": "§aShow all §ePlayers",
	"lobby.hide.button.hide": "§4Hide all §ePlayers",
	
	"lobby.ui.content.select.gadget": "§eSelect an §5Gadget§7.",
	"lobby.gadget.ui.button.particle": "§dParticles",
	"lobby.gadget.ui.button.fly": "§eFly",
    "lobby.gadget.ui.button.buyRanks": "§eBuy an §cRank",
	
	"lobby.settings.button.scoreboard": "§dScoreboard",
	
	"lobby.gadgets.title.particles": "§eParticles",
	
	"lobby.fly.ui.title": "§eFly",
	"lobby.ui.content.select.fly.mode": "{PREFIX} §eAktiviere den §aFlug§7-§aModus§7!",
	"ui.button.enableFly": "§aEnable §eFly",
	"ui.button.disableFly": "§cDisable §eFly",
	
	"lobby.enable.fly": "{PREFIX} §aYou have enabled the §eFly§7-§eMode§7!",
	"lobby.disable.fly": "{PREFIX} §cYou have disabled the §eFly§7-§eMode§7!",
	
	"lobby.ui.title.updates": "{PREFIX} §eUpdates",
	"lobby.ui.content.updates": "{PREFIX}\n\n§8- §eMLGRush Release§r\n\n§8- §cClanWars§e Beta§r\n\n§8- §eNew PrivateServer§7-§eSystem",
      
    "lobby.buyRank.alreadyHasRank": "{PREFIX} §cYou have already this §eRank§7.",
	
	"lobby.teleporter.button.spawn": "§l§7Spawn",
	"lobby.teleporter.button.bw": "§cBedWars",
	"lobby.teleporter.button.training": "§dTraining\n§8( §eWoolBattle §7/ §bMLGRush§7 / §eSpeedCW§8 )",	
	"lobby.teleporter.button.gungame": "§bGunGame",		
	"lobby.teleporter.button.ffa": "§eFFA§7-§eModes",
	"lobby.teleporter.button.pvpmode": "§2PvP\n§8( §eSumoPvP §7/ §dArenaPvP§7 / §aQSG§8 )",
      
    "lobby.title.confirm.buyRank": "§cConfirm your §epurchase",
    "lobby.rank.bought": "{PREFIX} §aYou have the rank #0# §asuccessfully bought§7!",
    "lobby.rank.buy.abort": "{PREFIX} §cYou have canceled the purchase§7.",
    "lobby.ui.content.confirm.Premium": "§7Rights for §6Premium Rank§7:\n\n§8- §eYou can §bFly in the §bLobby\n§8- §eYou own all §cParticles §in the §bLobby\n§8- §eYou can use the §dNick §eCommand\n\n§7Cost§8: §e30,000 Coins",
	"lobby.ui.content.confirm.Supreme": "§7The rights for the §bSupreme rank§7:\n\n§8- §eYou can start MiniGames\n§8- §eYou can choose a group (Premium) for your nickname\n§8- §eYou can create JoinMe's\n§8- §eAll the rights of the §6Premium§7-§6Rank\n\n§7Cost§8: §e150.000 Coins",
	
	"securitysystem.youCannotBanBypass": "{PREFIX} §cYou can't ban §e#0#§7!",
	"securitysystem.banWasSuccessfull": "{PREFIX} §aYou have banned §e#0# §abecasue of §e#1#§7!",
	"securitysystem.youCannotMuteBypass": "{PREFIX} §cYou can't mute §e#0#§7!",
	"securitysystem.muteWasSuccessfull": "{PREFIX} §aYou have muted §e#0# §abecasue of §e#1#§7!",
	"securitysystem.reportWasSuccessful": "{PREFIX} §aYou have reported §e#0# §abecasue of §e#1#§7!",
	"securitysystem.playerWasUnbanned": "{PREFIX} §e#0#§a was unbanned§7!",
	"securitysystem.playerWasUnmuted": "{PREFIX} §e#0#§a was unmuted§7!",
	"securitysystem.muted.automatic": "{PREFIX} §cYou are muted§7!\n§aDuration§7: §e#0#\n§aReason§7: §e#1#",
	"securitysystem.muted.permanent": "{PREFIX} §cYou are muted§7!\n§aMuted by§7: §e#0#\n§aReason§7: §e#1#",
	"securitysystem.muted.until": "{PREFIX} §cYou are muted§7!\n§aMuted by§7: §e#0#\n§aDuration§7: §e#1#\n§aReason§7: §e#2#",
	"securitysystem.banned.automatic": "{PREFIX} §4You was banned§7!\n§cBanned by§7:§e #0#\n§cReason§7:§e #1#\n§cDuration§7:§e #2#",
	"securitysystem.banned.permanent": "{PREFIX} §4You was banned§7!\n§cBanned by§7:§e #0#\n§cReason§7:§e #1#",
	"securitysystem.banned.until": "{PREFIX} §4You was banned§7!\n§cBanned by§7:§e #0#\n§cReason§7:§e #1#\n§cDuration§7:§e #2#",
	"securitysystem.playerNotBanned": "{PREFIX} §cThis player is not banned§7!",
	"securitysystem.playerNotMuted": "{PREFIX} §cThis player is not muted§7!",
	"securitysystem.youAreUnmuted.mistake": "{PREFIX} §aYour mute was removed because a §cmistake §awas made§7!",
	"securitysystem.youAreUnmuted": "{PREFIX} §aYou are no longer muted§7!",
	"securitysystem.noSpam": "{PREFIX} §cPlease don't spam§7!",
	"securitysystem.provideKickReason": "{PREFIX} §cPlease provide a reason§7!",
	"securitysystem.cantKickYourself": "{PREFIX} §cYou can't kick yourself§7!",
	"securitysystem.kickedPlayer": "{PREFIX} §aYou have kicked §e#0#§a because of §e#1#§7!",
	"securitysystem.noAds": "{PREFIX} §cPlease don't send Links§7!",
	"securitysystem.alreadyBanned": "{PREFIX} §cThis Player is already banned§7!",
	"securitysystem.alreadyMuted": "{PREFIX} §cThis Player is already muted§7!",
		
	"reason.tooManyCPS": "{PREFIX}\n §cYou have too many §eCPS§7.",
	
	"core.cps.logged": "{PREFIX} §aThe §eCPS§8-§eLog§a of §e#0#§a was created§7!\n§aHis §eCPS§7: §e#1#\n§r§8!!§cThe player may only be banned if he has 7000 CPS in 1 minute§8!!§r"
	}
}